symnum/__init__.py
symnum/_version.py
symnum/array.py
symnum/codegen.py
symnum/numpy.py
symnum/diffops/__init__.py
symnum/diffops/numpy.py
symnum/diffops/symbolic.py
symnum-0.2.1.dist-info/LICENSE
symnum-0.2.1.dist-info/METADATA
symnum-0.2.1.dist-info/WHEEL
symnum-0.2.1.dist-info/top_level.txt
symnum-0.2.1.dist-info/RECORD
