Metadata-Version: 2.1
Name: symnum
Version: 0.2.1
Summary: Symbolically construct NumPy functions and their derivatives.
Author-email: Matt Graham <m.graham@ucl.ac.uk>
Project-URL: homepage, https://github.com/matt-graham/symnum
Project-URL: documentation, https://matt-graham.github.io/symnum
Keywords: sympy,numpy,symbolic,differentiation
Classifier: Operating System :: OS Independent
Classifier: Topic :: Scientific/Engineering
Classifier: Intended Audience :: Science/Research
Classifier: Intended Audience :: Developers
Classifier: License :: OSI Approved :: MIT License
Classifier: Programming Language :: Python :: 3
Classifier: Programming Language :: Python :: 3 :: Only
Classifier: Programming Language :: Python :: 3.10
Classifier: Programming Language :: Python :: 3.11
Classifier: Programming Language :: Python :: 3.12
Classifier: Typing :: Typed
Requires-Python: >=3.10
License-File: LICENSE
Requires-Dist: numpy >=1.22
Requires-Dist: sympy >=1.8
Provides-Extra: dev
Requires-Dist: black ; extra == 'dev'
Requires-Dist: build ; extra == 'dev'
Requires-Dist: pytest ; extra == 'dev'
Requires-Dist: ruff ; extra == 'dev'
Requires-Dist: tox >=4 ; extra == 'dev'
Requires-Dist: twine ; extra == 'dev'
